SivantClass/__init__.py
SivantClass/sivant.py
Sivant-0.0.3.dist-info/LICENSE.txt
Sivant-0.0.3.dist-info/METADATA
Sivant-0.0.3.dist-info/WHEEL
Sivant-0.0.3.dist-info/top_level.txt
Sivant-0.0.3.dist-info/RECORD
